PeptideSearch/PeptideSearch.py
PeptideSearch/__init__.py
PeptidesSearch-0.3.5.dist-info/METADATA
PeptidesSearch-0.3.5.dist-info/WHEEL
PeptidesSearch-0.3.5.dist-info/top_level.txt
PeptidesSearch-0.3.5.dist-info/RECORD
