Metadata-Version: 2.1
Name: PeptidesSearch
Version: 0.3.5
Summary: Search a list of peptides in a fasta file (or proteome) and returns exact matches or hits with one mismatch
Home-page: https://github.com/khaledianehdieh/PeptidesSearch
Author: Ehdieh Khaledian
Author-email: khaledianehdieh@gmail.com
License: MIT
Download-URL: https://pypi.org/project/PeptidesSearch/
Keywords: Peptide Search,Peptide Match,One Mismatch,Exact Match,python,Peptide,Protein
Platform: UNKNOWN
Requires-Dist: pandas
Requires-Dist: numpy
Requires-Dist: more-itertools
